nonebot_plugin_humanaticstore/__init__.py
nonebot_plugin_humanaticstore/config.py
nonebot_plugin_humanaticstore/config_manager.py
nonebot_plugin_humanaticstore/nb_cli_command.py
nonebot_plugin_humanaticstore/utils.py
nonebot_plugin_humanaticstore-0.1.2.dist-info/LICENSE
nonebot_plugin_humanaticstore-0.1.2.dist-info/METADATA
nonebot_plugin_humanaticstore-0.1.2.dist-info/WHEEL
nonebot_plugin_humanaticstore-0.1.2.dist-info/RECORD
