Metadata-Version: 2.1
Name: nonebot_plugin_humanaticstore
Version: 0.1.2
Summary: 一个强大的配置管理工具集
License: GPL-3.0-or-later
Author: QuanhuZeyu
Author-email: 1624910218@qq.com
Requires-Python: >=3.8,<4.0
Classifier: License :: OSI Approved :: GNU General Public License v3 or later (GPLv3+)
Classifier: Programming Language :: Python :: 3
Classifier: Programming Language :: Python :: 3.8
Classifier: Programming Language :: Python :: 3.9
Classifier: Programming Language :: Python :: 3.10
Classifier: Programming Language :: Python :: 3.11
Classifier: Programming Language :: Python :: 3.12
Requires-Dist: nonebot2 (>=2.2.1,<3.0.0)
Requires-Dist: pydantic (>=2.6.4,<3.0.0)
Requires-Dist: pyyaml (>=6.0.1,<7.0.0)
Requires-Dist: typing-extensions (>=4.0.0,<5.0.0)
